{"name":"Json2sorttable","tagline":"create sortable html table from json format.","body":"json2sorttable\r\n==============\r\n\r\ncreate sortable html table from json format.\r\n\r\n##Preparation\r\n\r\n* Add script to html file <script src=\"jsonTable.js\"></script>\r\n* Your json (array) format should be an array which contains objects that have the same property like this...\r\n\r\n```\r\nvar yourJSON = [{a:1,b:'c'},{a:3,b:'b'},{a:5,b:'a'},...];\r\n```\r\n\r\n##How to used\r\n\r\n* Declare variable with your JSON for prepare them.\r\n\r\n```\r\nvar table = new jsonTable(yourJSON);\r\n```\r\n\r\n* Add it to your element with addTo(element).\r\n\r\n```\r\ntable.addTo(document.getElementById('contain'));\r\n```\r\n\r\n* Write your own styles with css if you want.\r\n\r\n##Manually sort\r\n* Just use sortWith(fieldName, element)\r\n\r\n```\r\ntable.sortWith('a', document.getElementById('contain'));\r\n```\r\n","google":"","note":"Don't delete this file! It's used internally to help with page regeneration."}